newnewid/__init__.py
newnewid/cli.py
newnewid/clock/uuid_clock.py
newnewid/counter/counter.py
newnewid/draft_ietf_uuidrev_rfc4122bis_00/__init__.py
newnewid/draft_ietf_uuidrev_rfc4122bis_00/nil_uuid_generator.py
newnewid/draft_ietf_uuidrev_rfc4122bis_01/__init__.py
newnewid/draft_ietf_uuidrev_rfc4122bis_02/__init__.py
newnewid/draft_ietf_uuidrev_rfc4122bis_03/__init__.py
newnewid/draft_peabody_dispatch_new_uuid_format_01/__init__.py
newnewid/draft_peabody_dispatch_new_uuid_format_01/uuid6_generator.py
newnewid/draft_peabody_dispatch_new_uuid_format_01/uuid7_generator.py
newnewid/draft_peabody_dispatch_new_uuid_format_01/uuid8_generator.py
newnewid/draft_peabody_dispatch_new_uuid_format_02/__init__.py
newnewid/draft_peabody_dispatch_new_uuid_format_03/__init__.py
newnewid/draft_peabody_dispatch_new_uuid_format_03/max_uuid_generator.py
newnewid/draft_peabody_dispatch_new_uuid_format_03/uuid7_generator.py
newnewid/draft_peabody_dispatch_new_uuid_format_03/uuid8_generator.py
newnewid/draft_peabody_dispatch_new_uuid_format_04/__init__.py
newnewid/exception/backward_uuid_exception.py
newnewid/parser/uuid_parser.py
newnewid/random/pseudo_random_binary_generator.py
newnewid/random/pseudo_random_generator.py
newnewid/util/nodoc.py
newnewid/util/specloader.py
newnewid/uuidgenerator/clock_based_uuid_generator.py
newnewid/uuidgenerator/gregorian_based_uuid_generator.py
newnewid/uuidgenerator/uuid_generator.py
newnewid-0.5.0.dist-info/LICENSE
newnewid-0.5.0.dist-info/METADATA
newnewid-0.5.0.dist-info/WHEEL
newnewid-0.5.0.dist-info/entry_points.txt
newnewid-0.5.0.dist-info/RECORD
