Metadata-Version: 2.1
Name: newnewid
Version: 0.5.0
Summary: 
Author: quwac
Author-email: 53551867+quwac@users.noreply.github.com
Requires-Python: >=3.8.1,<4.0.0
Classifier: Programming Language :: Python :: 3
Classifier: Programming Language :: Python :: 3.9
Classifier: Programming Language :: Python :: 3.10
Classifier: Programming Language :: Python :: 3.11
